{"v":"5.6.6","ip":0,"op":180,"fr":60,"w":1000,"h":1000,"layers":[{"ind":1865,"nm":"surface6733","ao":0,"ip":0,"op":264,"st":0,"ty":4,"ks":{"ty":"tr","o":{"k":100},"r":{"a":1,"k":[{"i":{"x":[0.67],"y":[1]},"o":{"x":[0.33],"y":[0]},"t":0,"s":[-1]},{"i":{"x":[0.67],"y":[1]},"o":{"x":[0.33],"y":[0]},"t":26,"s":[1]},{"i":{"x":[0.67],"y":[1]},"o":{"x":[0.33],"y":[0]},"t":59,"s":[-1]},{"i":{"x":[0.67],"y":[1]},"o":{"x":[0.33],"y":[0]},"t":85,"s":[1]},{"i":{"x":[0.67],"y":[1]},"o":{"x":[0.33],"y":[0]},"t":118,"s":[-1]},{"i":{"x":[0.67],"y":[1]},"o":{"x":[0.33],"y":[0]},"t":144,"s":[1]},{"t":177,"s":[-1]}],"ix":10},"p":{"a":1,"k":[{"i":{"x":0.67,"y":1},"o":{"x":0.33,"y":0},"t":0,"s":[0,0,0],"to":[0,4.17,0],"ti":[0,0,0]},{"i":{"x":0.67,"y":1},"o":{"x":0.33,"y":0},"t":44,"s":[0,25,0],"to":[0,0,0],"ti":[0,0,0]},{"i":{"x":0.67,"y":1},"o":{"x":0.33,"y":0},"t":90,"s":[0,0,0],"to":[0,0,0],"ti":[0,0,0]},{"i":{"x":0.67,"y":1},"o":{"x":0.33,"y":0},"t":134,"s":[0,25,0],"to":[0,0,0],"ti":[0,4.17,0]},{"t":180,"s":[0,0,0]}],"ix":2},"a":{"k":[0,0]},"s":{"k":[133.33,133.33]},"sk":{"k":0},"sa":{"k":0}},"shapes":[{"ty":"gr","hd":false,"nm":"surface6733","it":[{"ty":"gr","hd":false,"it":[{"ty":"sh","ks":{"k":{"i":[[0,0],[0,0],[29.48,0],[0,0],[1.24,29.48],[0,0],[-10.45,50.63]],"o":[[0,0],[-1.22,29.48],[0,0],[-29.48,0],[0,0],[11.91,52.7],[0,0]],"v":[[432.33,624.18],[431.45,646.07],[376.48,698.84],[375.4,698.84],[320.4,646.07],[319.52,624.18],[432.33,624.18]],"c":true}}},{"ty":"fl","o":{"k":100},"c":{"k":[0,0,0,1]}},{"ty":"tr","o":{"k":100},"r":{"k":0},"p":{"k":[0,0]},"a":{"k":[0,0]},"s":{"k":[100,100]},"sk":{"k":0},"sa":{"k":0},"hd":false}]},{"ty":"gr","hd":false,"it":[{"ty":"sh","ks":{"k":{"i":[[0,0],[12.21,-11.08],[0,0],[5.71,26.42],[-6.04,0],[0,0],[-4.03,-4.09]],"o":[[-5.65,27.86],[0,0],[-11.89,-13.43],[3.97,-3.89],[0,0],[6.17,0],[0,0]],"v":[[448.98,119.68],[423.91,182.65],[327.9,182.65],[303.31,119.27],[318.72,113.04],[433.15,113.04],[448.98,119.68]],"c":true}}},{"ty":"fl","o":{"k":100},"c":{"k":[0,0,0,1]}},{"ty":"tr","o":{"k":100},"r":{"k":0},"p":{"k":[0,0]},"a":{"k":[0,0]},"s":{"k":[100,100]},"sk":{"k":0},"sa":{"k":0},"hd":false}]},{"ty":"gr","hd":false,"it":[{"ty":"sh","ks":{"k":{"i":[[0,0],[0,0],[0,2.02],[0,0],[-2.02,0],[0,0],[0,-2.02],[0,0],[2.04,0]],"o":[[0,0],[-2.02,0],[0,0],[0,-2.02],[0,0],[2.02,0],[0,0],[0.02,2.03],[0,0]],"v":[[391.12,306.02],[360.71,306.02],[357.04,302.36],[357.04,302.27],[360.71,298.61],[391.12,298.61],[394.79,302.27],[394.79,302.36],[391.12,306.02]],"c":true}}},{"ty":"fl","o":{"k":100},"c":{"k":[0,0,0,1]}},{"ty":"tr","o":{"k":100},"r":{"k":0},"p":{"k":[0,0]},"a":{"k":[0,0]},"s":{"k":[100,100]},"sk":{"k":0},"sa":{"k":0},"hd":false}]},{"ty":"gr","hd":false,"it":[{"ty":"sh","ks":{"k":{"i":[[0,0],[0,0],[0.04,-2],[0,0],[0,0],[0,0],[1.26,0]],"o":[[0,0],[-1.26,0],[0,0],[0,0],[0,0],[-0.02,-2],[0,0]],"v":[[443.21,49.18],[443.17,49.18],[440.85,52.77],[438.84,129.82],[447.54,129.82],[445.54,52.77],[443.21,49.18]],"c":true}}},{"ty":"fl","o":{"k":100},"c":{"k":[0,0,0,1]}},{"ty":"tr","o":{"k":100},"r":{"k":0},"p":{"k":[0,0]},"a":{"k":[0,0]},"s":{"k":[100,100]},"sk":{"k":0},"sa":{"k":0},"hd":false}]},{"ty":"gr","hd":false,"it":[{"ty":"sh","ks":{"k":{"i":[[0,0],[0,0],[0.04,-2],[0,0],[0,0],[0,0],[1.26,0]],"o":[[0,0],[-1.26,0],[0,0],[0,0],[0,0],[-0.02,-2],[0,0]],"v":[[421.16,49.18],[421.12,49.18],[418.8,52.77],[416.8,129.82],[425.5,129.82],[423.49,52.77],[421.16,49.18]],"c":true}}},{"ty":"fl","o":{"k":100},"c":{"k":[0,0,0,1]}},{"ty":"tr","o":{"k":100},"r":{"k":0},"p":{"k":[0,0]},"a":{"k":[0,0]},"s":{"k":[100,100]},"sk":{"k":0},"sa":{"k":0},"hd":false}]},{"ty":"gr","hd":false,"it":[{"ty":"sh","ks":{"k":{"i":[[0,0],[0,0],[0.04,-2],[0,0],[0,0],[0,0],[1.27,0]],"o":[[0,0],[-1.26,0],[0,0],[0,0],[0,0],[-0.04,-2],[0,0]],"v":[[399.11,49.18],[399.07,49.18],[396.75,52.77],[394.75,129.82],[403.45,129.82],[401.44,52.77],[399.11,49.18]],"c":true}}},{"ty":"fl","o":{"k":100},"c":{"k":[0,0,0,1]}},{"ty":"tr","o":{"k":100},"r":{"k":0},"p":{"k":[0,0]},"a":{"k":[0,0]},"s":{"k":[100,100]},"sk":{"k":0},"sa":{"k":0},"hd":false}]},{"ty":"gr","hd":false,"it":[{"ty":"sh","ks":{"k":{"i":[[0,0],[0,0],[0.04,-2],[0,0],[0,0],[0,0],[1.26,0]],"o":[[0,0],[-1.26,0],[0,0],[0,0],[0,0],[-0.04,-2],[0,0]],"v":[[377.07,49.18],[377.03,49.18],[374.7,52.77],[372.7,129.82],[381.4,129.82],[379.39,52.77],[377.07,49.18]],"c":true}}},{"ty":"fl","o":{"k":100},"c":{"k":[0,0,0,1]}},{"ty":"tr","o":{"k":100},"r":{"k":0},"p":{"k":[0,0]},"a":{"k":[0,0]},"s":{"k":[100,100]},"sk":{"k":0},"sa":{"k":0},"hd":false}]},{"ty":"gr","hd":false,"it":[{"ty":"sh","ks":{"k":{"i":[[0,0],[0,0],[0.04,-2],[0,0],[0,0],[0,0],[1.24,0]],"o":[[0,0],[-1.26,0],[0,0],[0,0],[0,0],[-0.04,-2],[0,0]],"v":[[355.02,49.18],[354.98,49.18],[352.66,52.77],[350.65,129.82],[359.35,129.82],[357.35,52.77],[355.02,49.18]],"c":true}}},{"ty":"fl","o":{"k":100},"c":{"k":[0,0,0,1]}},{"ty":"tr","o":{"k":100},"r":{"k":0},"p":{"k":[0,0]},"a":{"k":[0,0]},"s":{"k":[100,100]},"sk":{"k":0},"sa":{"k":0},"hd":false}]},{"ty":"gr","hd":false,"it":[{"ty":"sh","ks":{"k":{"i":[[0,0],[0,0],[0.04,-2],[0,0],[0,0],[0,0],[1.26,0]],"o":[[0,0],[-1.26,0],[0,0],[0,0],[0,0],[-0.02,-2],[0,0]],"v":[[332.95,49.18],[332.91,49.18],[330.59,52.77],[328.58,129.82],[337.28,129.82],[335.28,52.77],[332.95,49.18]],"c":true}}},{"ty":"fl","o":{"k":100},"c":{"k":[0,0,0,1]}},{"ty":"tr","o":{"k":100},"r":{"k":0},"p":{"k":[0,0]},"a":{"k":[0,0]},"s":{"k":[100,100]},"sk":{"k":0},"sa":{"k":0},"hd":false}]},{"ty":"gr","hd":false,"it":[{"ty":"sh","ks":{"k":{"i":[[0,0],[0,0],[0.04,-2],[0,0],[0,0],[0,0],[1.26,0]],"o":[[0,0],[-1.26,0],[0,0],[0,0],[0,0],[-0.04,-2],[0,0]],"v":[[310.9,49.18],[310.86,49.18],[308.54,52.77],[306.54,129.82],[315.23,129.82],[313.23,52.77],[310.9,49.18]],"c":true}}},{"ty":"fl","o":{"k":100},"c":{"k":[0,0,0,1]}},{"ty":"tr","o":{"k":100},"r":{"k":0},"p":{"k":[0,0]},"a":{"k":[0,0]},"s":{"k":[100,100]},"sk":{"k":0},"sa":{"k":0},"hd":false}]},{"ty":"gr","hd":false,"it":[{"ty":"sh","ks":{"k":{"i":[[0,0],[0,0],[0,0],[0,0]],"o":[[0,0],[0,0],[0,0],[0,0]],"v":[[307.07,94.34],[443.19,94.34],[443.19,99.89],[307.07,99.89]],"c":true}}},{"ty":"fl","o":{"k":100},"c":{"k":[0.8,0.8,0.8,1]}},{"ty":"tr","o":{"k":100},"r":{"k":0},"p":{"k":[0,0]},"a":{"k":[0,0]},"s":{"k":[100,100]},"sk":{"k":0},"sa":{"k":0},"hd":false}]},{"ty":"gr","hd":false,"it":[{"ty":"sh","ks":{"k":{"i":[[0,0],[0,0],[0,0],[0,0]],"o":[[0,0],[0,0],[0,0],[0,0]],"v":[[307.07,94.34],[443.19,94.34],[443.19,119.26],[307.07,119.26]],"c":true}}},{"ty":"fl","o":{"k":100},"c":{"k":[1,1,1,1]}},{"ty":"tr","o":{"k":100},"r":{"k":0},"p":{"k":[0,0]},"a":{"k":[0,0]},"s":{"k":[100,100]},"sk":{"k":0},"sa":{"k":0},"hd":false}]},{"ty":"gr","hd":false,"it":[{"ty":"sh","ks":{"k":{"i":[[0,0],[0,0],[0,2.02],[0,0],[-2.02,0],[0,0],[0,-2.02],[0,0],[2.04,0]],"o":[[0,0],[-2.02,0],[0,0],[0,-2.02],[0,0],[2.02,0],[0,0],[0.02,2.02],[0,0]],"v":[[391.12,291.19],[360.71,291.19],[357.04,287.52],[357.04,287.44],[360.71,283.77],[391.12,283.77],[394.79,287.44],[394.79,287.52],[391.12,291.19]],"c":true}}},{"ty":"fl","o":{"k":100},"c":{"k":[0,0,0,1]}},{"ty":"tr","o":{"k":100},"r":{"k":0},"p":{"k":[0,0]},"a":{"k":[0,0]},"s":{"k":[100,100]},"sk":{"k":0},"sa":{"k":0},"hd":false}]},{"ty":"gr","hd":false,"it":[{"ty":"sh","ks":{"k":{"i":[[0,0],[0,0],[0,2.02],[0,0],[-2.02,0],[0,0],[0,-2.02],[0,0],[2.04,0]],"o":[[0,0],[-2.02,0],[0,0],[0,-2.02],[0,0],[2.02,0],[0,0],[0.02,2.02],[0,0]],"v":[[391.12,276.36],[360.71,276.36],[357.04,272.69],[357.04,272.61],[360.71,268.95],[391.12,268.95],[394.79,272.61],[394.79,272.7],[391.12,276.36]],"c":true}}},{"ty":"fl","o":{"k":100},"c":{"k":[0,0,0,1]}},{"ty":"tr","o":{"k":100},"r":{"k":0},"p":{"k":[0,0]},"a":{"k":[0,0]},"s":{"k":[100,100]},"sk":{"k":0},"sa":{"k":0},"hd":false}]},{"ty":"gr","hd":false,"it":[{"ty":"sh","ks":{"k":{"i":[[0,0],[0,0],[0,2.02],[0,0],[-2.02,0],[0,0],[0,-2.02],[0,0],[2.04,0]],"o":[[0,0],[-2.02,0],[0,0],[0,-2.02],[0,0],[2.02,0],[0,0],[0.02,2.02],[0,0]],"v":[[391.12,261.53],[360.71,261.53],[357.04,257.86],[357.04,257.78],[360.71,254.11],[391.12,254.11],[394.79,257.78],[394.79,257.86],[391.12,261.53]],"c":true}}},{"ty":"fl","o":{"k":100},"c":{"k":[0,0,0,1]}},{"ty":"tr","o":{"k":100},"r":{"k":0},"p":{"k":[0,0]},"a":{"k":[0,0]},"s":{"k":[100,100]},"sk":{"k":0},"sa":{"k":0},"hd":false}]},{"ty":"gr","hd":false,"it":[{"ty":"sh","ks":{"k":{"i":[[0,0],[0,0],[0,14.55],[0,0],[-14.55,0],[0,0],[0,-14.55],[0,0],[14.57,0]],"o":[[0,0],[-14.55,0],[0,0],[0,-14.55],[0,0],[14.55,0],[0,0],[0,14.55],[0,0]],"v":[[376.18,440.16],[375.64,440.16],[349.28,413.8],[349.28,373.25],[375.64,346.89],[376.18,346.89],[402.54,373.25],[402.54,413.8],[376.18,440.16]],"c":true}}},{"ty":"fl","o":{"k":100},"c":{"k":[0,0,0,1]}},{"ty":"tr","o":{"k":100},"r":{"k":0},"p":{"k":[0,0]},"a":{"k":[0,0]},"s":{"k":[100,100]},"sk":{"k":0},"sa":{"k":0},"hd":false}]},{"ty":"gr","hd":false,"it":[{"ty":"sh","ks":{"k":{"i":[[0,0],[0,0],[0,-26.24],[0,0],[-26.24,0],[0,0],[0,-26.24],[0,0],[26.23,0]],"o":[[0,0],[-26.26,0],[0,0],[0,-26.26],[0,0],[26.26,0],[0,0],[0,-26.26],[0,0]],"v":[[376.41,232.54],[375.45,232.54],[327.92,280.07],[327.92,284.12],[375.45,236.59],[376.41,236.59],[423.93,284.12],[423.93,280.07],[376.41,232.54]],"c":true}}},{"ty":"fl","o":{"k":100},"c":{"k":[0.44,0.34,0.34,1]}},{"ty":"tr","o":{"k":100},"r":{"k":0},"p":{"k":[0,0]},"a":{"k":[0,0]},"s":{"k":[100,100]},"sk":{"k":0},"sa":{"k":0},"hd":false}]},{"ty":"gr","hd":false,"it":[{"ty":"sh","ks":{"k":{"i":[[0,0],[0,0],[0,26.24],[0,0],[-26.24,0],[0,0],[0,-26.24],[0,0],[26.23,0]],"o":[[0,0],[-26.26,0],[0,0],[0,-26.26],[0,0],[26.26,0],[0,0],[0,26.24],[0,0]],"v":[[376.41,461.22],[375.45,461.22],[327.92,413.7],[327.92,280.07],[375.45,232.54],[376.41,232.54],[423.93,280.07],[423.93,413.7],[376.41,461.22]],"c":true}}},{"ty":"fl","o":{"k":100},"c":{"k":[1,1,1,1]}},{"ty":"tr","o":{"k":100},"r":{"k":0},"p":{"k":[0,0]},"a":{"k":[0,0]},"s":{"k":[100,100]},"sk":{"k":0},"sa":{"k":0},"hd":false}]},{"ty":"gr","hd":false,"it":[{"ty":"sh","ks":{"k":{"i":[[0,0],[0,0],[0,0],[0,0]],"o":[[0,0],[0,0],[0,0],[0,0]],"v":[[352.31,451.62],[399.5,451.62],[399.5,668.68],[352.31,668.68]],"c":true}}},{"ty":"fl","o":{"k":100},"c":{"k":[0,0,0,1]}},{"ty":"tr","o":{"k":100},"r":{"k":0},"p":{"k":[0,0]},"a":{"k":[0,0]},"s":{"k":[100,100]},"sk":{"k":0},"sa":{"k":0},"hd":false}]},{"ty":"gr","hd":false,"it":[{"ty":"sh","ks":{"k":{"i":[[0,0],[0,0],[2.56,0],[0,0],[0.12,-2.62],[0,0],[0,0],[27.96,0],[0,0],[8.64,17.96],[0.34,8.14],[0,0],[0,0],[2.48,0],[0,0],[0,2.71],[0,0],[-4.07,4.05],[-5.71,0],[0,0],[-3.83,-4.09],[0,-6.11]],"o":[[0,0],[0,2.71],[0,0],[-2.48,0],[0,0],[0,0],[-1.14,29.48],[0,0],[-20.25,0],[-3.31,-6.84],[0,0],[0,0],[-0.12,-2.62],[0,0],[-2.57,0],[0,0],[0,-6.36],[3.75,-3.89],[0,0],[5.87,0],[3.83,4.03],[0,0]],"v":[[451.33,135.37],[451.33,296.3],[446.7,301.19],[446.58,301.19],[441.93,305.88],[429.4,624.18],[428.56,646.07],[376.45,698.84],[375.4,698.84],[328.84,668.68],[323.25,646.07],[322.4,624.18],[309.9,305.88],[305.27,301.19],[305.15,301.19],[300.5,296.3],[300.5,135.37],[307.05,119.28],[321.67,113.04],[430.14,113.04],[445.18,119.68],[451.33,135.37]],"c":true}}},{"ty":"fl","o":{"k":100},"c":{"k":[1,0,0,1]}},{"ty":"tr","o":{"k":100},"r":{"k":0},"p":{"k":[0,0]},"a":{"k":[0,0]},"s":{"k":[100,100]},"sk":{"k":0},"sa":{"k":0},"hd":false}]},{"ty":"gr","hd":false,"it":[{"ty":"sh","ks":{"k":{"i":[[0,0],[0,0],[2.71,0],[0,0],[0.12,-2.62],[0,0],[0,0],[29.48,0],[0,0],[9.1,17.96],[0.38,8.14],[0,0],[0,0],[2.62,0],[0,0],[0,2.71],[0,0],[-4.29,4.05],[-6.04,0],[0,0],[-4.05,-4.09],[0,-6.11]],"o":[[0,0],[0,2.71],[0,0],[-2.62,0],[0,0],[0,0],[-1.22,29.48],[0,0],[-21.35,0],[-3.49,-6.84],[0,0],[0,0],[-0.12,-2.62],[0,0],[-2.71,0],[0,0],[0,-6.36],[3.97,-3.89],[0,0],[6.2,0],[3.99,4.03],[0,0]],"v":[[455.46,135.37],[455.46,296.3],[450.57,301.19],[450.45,301.19],[445.55,305.88],[432.32,624.2],[431.44,646.09],[376.48,698.86],[375.4,698.86],[326.29,668.7],[320.38,646.09],[319.5,624.2],[306.29,305.88],[301.4,301.19],[301.28,301.19],[296.39,296.3],[296.39,135.37],[303.3,119.28],[318.72,113.04],[433.15,113.04],[449,119.68],[455.46,135.37]],"c":true}}},{"ty":"fl","o":{"k":100},"c":{"k":[0,0,0,1]}},{"ty":"tr","o":{"k":100},"r":{"k":0},"p":{"k":[0,0]},"a":{"k":[0,0]},"s":{"k":[100,100]},"sk":{"k":0},"sa":{"k":0},"hd":false}]},{"ty":"tr","o":{"k":100},"r":{"k":0},"p":{"k":[0,0]},"a":{"k":[0,0]},"s":{"k":[100,100]},"sk":{"k":0},"sa":{"k":0},"hd":false}]}]}],"meta":{"g":"LF SVG to Lottie"}}